surge/__init__.py
surge/api_resource.py
surge/carousel.py
surge/errors.py
surge/projects.py
surge/questions.py
surge/reports.py
surge/responses.py
surge/rubrics.py
surge/tasks.py
surge/teams.py
surge/utils.py
surge_api-1.5.20.dist-info/licenses/LICENSE
surge_api-1.5.20.dist-info/METADATA
surge_api-1.5.20.dist-info/WHEEL
surge_api-1.5.20.dist-info/top_level.txt
surge_api-1.5.20.dist-info/RECORD
