Metadata-Version: 2.4
Name: surge-api
Version: 1.5.20
Summary: Surge Python SDK
Home-page: https://github.com/surge-ai/surge-python
Author: Surge
Author-email: team@surgehq.ai
License: MIT
Requires-Python: >=3.9
License-File: LICENSE
Requires-Dist: certifi==2025.10.5
Requires-Dist: charset-normalizer==3.4.3
Requires-Dist: idna==3.10
Requires-Dist: iniconfig==2.1.0
Requires-Dist: packaging==25.0
Requires-Dist: pluggy==1.6.0
Requires-Dist: pytest==8.4.2
Requires-Dist: python-dateutil==2.9.0.post0
Requires-Dist: requests==2.32.5
Requires-Dist: six==1.17.0
Requires-Dist: urllib3==2.5.0
Dynamic: author
Dynamic: author-email
Dynamic: description
Dynamic: description-content-type
Dynamic: home-page
Dynamic: license
Dynamic: license-file
Dynamic: requires-dist
Dynamic: requires-python
Dynamic: summary
